pi3dec/__init__.py
pi3dec/calibration.py
pi3dec/experiment.py
pi3dec/od_measurement.py
pi3dec/photodiodes.py
pi3dec/plotting.py
pi3dec/pumps.py
pi3dec/telegram.py
pi3dec/valves.py
pi3dec/pm/__init__.py
pi3dec/pm/device_messages_pb2.py
pi3dec/pm/network_messages_pb2.py
pi3dec/pm/protobuf_to_dict.py
pi3dec-0.68.dist-info/METADATA
pi3dec-0.68.dist-info/WHEEL
pi3dec-0.68.dist-info/top_level.txt
pi3dec-0.68.dist-info/zip-safe
pi3dec-0.68.dist-info/RECORD
