Metadata-Version: 2.1
Name: pi3dec
Version: 0.68
Summary: PMachine Python package
Home-page: https://github.com/catalin-rusnac/pizdets
Author: Catalin Rusnac
Author-email: crusnac@ist.ac.at
License: MIT
Platform: UNKNOWN
Requires-Python: >=3.0
Requires-Dist: zmq
Requires-Dist: google
Requires-Dist: pandas
Requires-Dist: protobuf
Requires-Dist: matplotlib
Requires-Dist: schedule
